README.md
run_avalon_bot
setup.py
avalonbot/__init__.py
avalonbot/bot.py
avalonbot/cards.py
avalonbot/game.py
avalonbot.egg-info/PKG-INFO
avalonbot.egg-info/SOURCES.txt
avalonbot.egg-info/dependency_links.txt
avalonbot.egg-info/top_level.txt