Metadata-Version: 1.0
Name: avalonbot
Version: 0.2.0.0
Summary: Bot for doing initial avalon card assignments
Home-page: https://github.com/AvantiShri/avalon-bot
Author: Av Shrikumar
Author-email: avanti.shrikumar@gmail.com
License: UNKNOWN
Platform: UNKNOWN
